README.md
setup.py
nxaddons/__init__.py
nxaddons/nx3d.py
nxaddons.egg-info/PKG-INFO
nxaddons.egg-info/SOURCES.txt
nxaddons.egg-info/dependency_links.txt
nxaddons.egg-info/not-zip-safe
nxaddons.egg-info/requires.txt
nxaddons.egg-info/top_level.txt