Metadata-Version: 1.1
Name: nxaddons
Version: 0.0.2
Summary: Extended tools for NetworkX package
Home-page: https://github.com/harsgak/nxaddons
Author: harsgak
Author-email: harsgak@yahoo.com
License: MIT
Platform: UNKNOWN
Classifier: Development Status :: 1 - Planning
Classifier: License :: OSI Approved :: MIT License
